optunity/communication.py
optunity/constraints.py
optunity/util.py
optunity/standalone.py
optunity/functions.py
optunity/__init__.py
optunity/metrics.py
optunity/parallel.py
optunity/search_spaces.py
optunity/cross_validation.py
optunity/api.py
optunity/solvers/CMAES.py
optunity/solvers/util.py
optunity/solvers/RandomSearch.py
optunity/solvers/GridSearch.py
optunity/solvers/solver_registry.py
optunity/solvers/__init__.py
optunity/solvers/ParticleSwarm.py
optunity/solvers/NelderMead.py
optunity/solvers/TPE.py
optunity/solvers/Sobol.py
optunity/tests/test_solvers.py
optunity/tests/test_all.py
optunity/tests/__init__.py
Optunity-1.1.0.dist-info/RECORD
Optunity-1.1.0.dist-info/METADATA
Optunity-1.1.0.dist-info/metadata.json
Optunity-1.1.0.dist-info/top_level.txt
Optunity-1.1.0.dist-info/DESCRIPTION.rst
Optunity-1.1.0.dist-info/WHEEL
