Metadata-Version: 2.0
Name: Optunity
Version: 1.1.0
Summary: Optimization routines for hyperparameter tuning.
Home-page: http://www.optunity.net
Author: Marc Claesen
Author-email: marc.claesen@esat.kuleuven.be
License: LICENSE.txt
Keywords: machine learning,parameter tuning,hyperparameter optimization,meta-optimization,direct search,model selection,particle swarm optimization
Platform: any
Classifier: Development Status :: 5 - Production/Stable
Classifier: Intended Audience :: Developers
Classifier: Intended Audience :: Education
Classifier: Intended Audience :: Science/Research
Classifier: Programming Language :: Python
Classifier: License :: OSI Approved :: BSD License
Classifier: Topic :: Scientific/Engineering
Classifier: Topic :: Scientific/Engineering :: Artificial Intelligence
Classifier: Topic :: Scientific/Engineering :: Information Analysis
Classifier: Programming Language :: Python :: 2.7
Classifier: Programming Language :: Python :: 3
Classifier: Programming Language :: Python :: 3.2
Classifier: Programming Language :: Python :: 3.3
Classifier: Programming Language :: Python :: 3.4
